generalrepytivity/__init__.py
generalrepytivity-0.1.0.dist-info/DESCRIPTION.rst
generalrepytivity-0.1.0.dist-info/METADATA
generalrepytivity-0.1.0.dist-info/RECORD
generalrepytivity-0.1.0.dist-info/WHEEL
generalrepytivity-0.1.0.dist-info/metadata.json
generalrepytivity-0.1.0.dist-info/top_level.txt
