Metadata-Version: 2.0
Name: generalrepytivity
Version: 0.1.0
Summary: generalrelativity holds some algorithms that render useful when doing computations related to general relativity.
Home-page: https://github.com/miguelgondu/generalrepytivity
Author: Miguel Gonzalez Duque
Author-email: miguelgondu@gmail.com
License: MIT license
Keywords: generalrepytivity
Platform: UNKNOWN
Classifier: Development Status :: 2 - Pre-Alpha
Classifier: Intended Audience :: Developers
Classifier: License :: OSI Approved :: MIT License
Classifier: Natural Language :: English
Classifier: Programming Language :: Python :: 3
Classifier: Programming Language :: Python :: 3.4
Classifier: Programming Language :: Python :: 3.5
Classifier: Programming Language :: Python :: 3.6
Requires-Dist: sympy
